ctlogger/__init__.py
ctlogger/logger.py
ctlogger/sendgrid.py
ctlogger/slack.py
ctlogger/test_logger.py
ctlogger/test_notify.py
ctlogger-0.0.3.dist-info/DESCRIPTION.rst
ctlogger-0.0.3.dist-info/METADATA
ctlogger-0.0.3.dist-info/RECORD
ctlogger-0.0.3.dist-info/WHEEL
ctlogger-0.0.3.dist-info/metadata.json
ctlogger-0.0.3.dist-info/top_level.txt
