Metadata-Version: 2.0
Name: ctlogger
Version: 0.0.3
Summary: A python log utils, such as colorful log on terminal, notify by slack or email
Home-page: https://github.com/sdf611097/py-logger
Author: ChunTing Lin
Author-email: sdf611097@gmail.com
License: MIT
Keywords: logger log color color-console notify slack sendgrid
Platform: UNKNOWN
Classifier: Development Status :: 3 - Alpha
Classifier: Programming Language :: Python :: 3 :: Only
Requires-Dist: requests
